trampoline/__init__.py
trampoline-0.1.1.dist-info/METADATA
trampoline-0.1.1.dist-info/RECORD
trampoline-0.1.1.dist-info/WHEEL
trampoline-0.1.1.dist-info/top_level.txt
