Metadata-Version: 2.1
Name: trampoline
Version: 0.1.1
Summary: Simple and tiny yield-based trampoline implementation.
Home-page: https://gitlab.com/ferreum/trampoline
Author: UNKNOWN
Author-email: code.danielk@gmail.com
License: MIT
Keywords: trampoline recursion tail call
Platform: UNKNOWN
Classifier: Development Status :: 3 - Alpha
Classifier: Intended Audience :: Developers
Classifier: License :: OSI Approved :: MIT License
Classifier: Natural Language :: English
Classifier: Operating System :: OS Independent
Classifier: Programming Language :: Python :: 3.5
Classifier: Programming Language :: Python :: 3.6
Classifier: Programming Language :: Python :: 3.7
